dataset_iterator/__init__.py
dataset_iterator/concat_iterator.py
dataset_iterator/hard_sample_mining.py
dataset_iterator/helpers.py
dataset_iterator/image_data_generator.py
dataset_iterator/index_array_iterator.py
dataset_iterator/keras_callbacks.py
dataset_iterator/multichannel_iterator.py
dataset_iterator/nonvoid_iterator.py
dataset_iterator/ordered_enqueuer_cf.py
dataset_iterator/pre_processing.py
dataset_iterator/process_utils.py
dataset_iterator/shared_memory.py
dataset_iterator/tile_utils.py
dataset_iterator/tracking_iterator.py
dataset_iterator/utils.py
dataset_iterator/validation_callback.py
dataset_iterator/datasetIO/__init__.py
dataset_iterator/datasetIO/concatenate_datasetIO.py
dataset_iterator/datasetIO/datasetIO.py
dataset_iterator/datasetIO/group_datasetIO.py
dataset_iterator/datasetIO/h5pyIO.py
dataset_iterator/datasetIO/memoryIO.py
dataset_iterator/datasetIO/multiple_datasetIO.py
dataset_iterator/datasetIO/multiple_fileIO.py
dataset_iterator-0.5.7.dist-info/licenses/LICENSE.txt
dataset_iterator-0.5.7.dist-info/METADATA
dataset_iterator-0.5.7.dist-info/WHEEL
dataset_iterator-0.5.7.dist-info/top_level.txt
dataset_iterator-0.5.7.dist-info/RECORD
