Metadata-Version: 2.4
Name: dataset_iterator
Version: 0.5.7
Summary: Keras-style data iterator for images contained in dataset files such as hdf5 or PIL readable files. Images can be contained in several files.
Home-page: https://github.com/jeanollion/dataset_iterator.git
Download-URL: https://github.com/jeanollion/dataset_iterator/releases/download/v0.5.7/dataset_iterator-0.5.7.tar.gz
Author: Jean Ollion
Author-email: jean.ollion@sabilab.fr
Keywords: Iterator,Dataset,Image,Numpy
Classifier: Development Status :: 4 - Beta
Classifier: Intended Audience :: Science/Research
Classifier: Topic :: Scientific/Engineering :: Artificial Intelligence
Classifier: Topic :: Scientific/Engineering :: Image Processing
Classifier: Topic :: Scientific/Engineering :: Artificial Intelligence
Classifier: License :: OSI Approved :: GNU General Public License v3 or later (GPLv3+)
Classifier: Programming Language :: Python :: 3
Requires-Python: >=3
License-File: LICENSE.txt
Requires-Dist: h5py>=2.9
Requires-Dist: numpy
Requires-Dist: scipy
Requires-Dist: scikit-learn
Requires-Dist: scikit-image
Requires-Dist: tensorflow>=2.7.1
Requires-Dist: keras
Requires-Dist: psutil
Requires-Dist: dill
Dynamic: author
Dynamic: author-email
Dynamic: classifier
Dynamic: description
Dynamic: description-content-type
Dynamic: download-url
Dynamic: home-page
Dynamic: keywords
Dynamic: license-file
Dynamic: requires-dist
Dynamic: requires-python
Dynamic: summary
